lg.py
setup.py
py_lookingglass.egg-info/PKG-INFO
py_lookingglass.egg-info/SOURCES.txt
py_lookingglass.egg-info/dependency_links.txt
py_lookingglass.egg-info/entry_points.txt
py_lookingglass.egg-info/requires.txt
py_lookingglass.egg-info/top_level.txt