Metadata-Version: 1.1
Name: py-lookingglass
Version: 1.01
Summary: Python looking glass WSGI implementation
Home-page: https://github.com/andrew-azarov/py-lookingglass
Author: Andrew Azarov
Author-email: andrew@serverastra.com
License: MIT
Download-URL: https://github.com/ServerAstra/py-lookingglass/tarball/master
Platform: UNKNOWN
Classifier: Development Status :: 5 - Production/Stable
Classifier: Environment :: Web Environment
Classifier: Intended Audience :: Telecommunications Industry
Classifier: Intended Audience :: System Administrators
Classifier: Intended Audience :: Information Technology
Classifier: License :: OSI Approved :: MIT License
Classifier: Operating System :: POSIX
Classifier: Topic :: Internet :: WWW/HTTP :: WSGI :: Application
Classifier: Topic :: System :: Networking
Classifier: Topic :: System :: Systems Administration
